goatcounter_mcp_server/__init__.py
goatcounter_mcp_server/server.py
goatcounter_mcp_server-0.2.4.dist-info/METADATA
goatcounter_mcp_server-0.2.4.dist-info/WHEEL
goatcounter_mcp_server-0.2.4.dist-info/entry_points.txt
goatcounter_mcp_server-0.2.4.dist-info/licenses/LICENSE
goatcounter_mcp_server-0.2.4.dist-info/RECORD
