Metadata-Version: 2.4
Name: goatcounter-mcp-server
Version: 0.2.4
Summary: Goatcounter API tool for FastMCP
Project-URL: Homepage, https://github.com/rafaljanicki/goatcounter-mcp-server
Project-URL: Issues, https://github.com/rafaljanicki/goatcounter-mcp-server/issues
Author-email: Rafal Janicki <rafal@kult.io>
License-Expression: MIT
License-File: LICENSE
Classifier: License :: OSI Approved :: MIT License
Classifier: Operating System :: OS Independent
Classifier: Programming Language :: Python :: 3
Classifier: Programming Language :: Python :: 3.10
Classifier: Programming Language :: Python :: 3.11
Classifier: Programming Language :: Python :: 3.12
Classifier: Programming Language :: Python :: 3.13
Requires-Python: >=3.10
Requires-Dist: fastmcp>=2.2.6
Requires-Dist: httpx>=0.28.1
Requires-Dist: pydantic>=2.11.4
Requires-Dist: python-dotenv>=1.1.0
